codeoptix/__init__.py
codeoptix/cli.py
codeoptix/acp/__init__.py
codeoptix/acp/agent.py
codeoptix/acp/bridge.py
codeoptix/acp/client_adapter.py
codeoptix/acp/code_extractor.py
codeoptix/acp/orchestrator.py
codeoptix/acp/registry.py
codeoptix/adapters/__init__.py
codeoptix/adapters/base.py
codeoptix/adapters/basic.py
codeoptix/adapters/claude_code.py
codeoptix/adapters/codex.py
codeoptix/adapters/factory.py
codeoptix/adapters/gemini_cli.py
codeoptix/artifacts/__init__.py
codeoptix/artifacts/manager.py
codeoptix/behaviors/__init__.py
codeoptix/behaviors/base.py
codeoptix/behaviors/insecure_code.py
codeoptix/behaviors/plan_drift.py
codeoptix/behaviors/vacuous_tests.py
codeoptix/evaluation/__init__.py
codeoptix/evaluation/bloom_integration.py
codeoptix/evaluation/engine.py
codeoptix/evaluation/evaluators.py
codeoptix/evaluation/scenario_generator.py
codeoptix/evolution/__init__.py
codeoptix/evolution/engine.py
codeoptix/evolution/gepa_integration.py
codeoptix/evolution/proposer.py
codeoptix/linters/__init__.py
codeoptix/linters/bandit_linter.py
codeoptix/linters/base.py
codeoptix/linters/coverage_linter.py
codeoptix/linters/flake8_linter.py
codeoptix/linters/html_accessibility_linter.py
codeoptix/linters/language_detector.py
codeoptix/linters/mypy_linter.py
codeoptix/linters/pip_audit_linter.py
codeoptix/linters/pylint_linter.py
codeoptix/linters/ruff_linter.py
codeoptix/linters/runner.py
codeoptix/linters/safety_linter.py
codeoptix/reflection/__init__.py
codeoptix/reflection/engine.py
codeoptix/reflection/generator.py
codeoptix/utils/__init__.py
codeoptix/utils/config.py
codeoptix/utils/llm.py
codeoptix/utils/retry.py
codeoptix/vendor/__init__.py
codeoptix/vendor/bloom/README.md
codeoptix/vendor/bloom/__init__.py
codeoptix/vendor/bloom/globals.py
codeoptix/vendor/bloom/transcript_utils.py
codeoptix/vendor/bloom/utils.py
codeoptix/vendor/bloom/orchestrators/ConversationOrchestrator.py
codeoptix/vendor/bloom/orchestrators/SimEnvOrchestrator.py
codeoptix-0.1.3.dist-info/licenses/LICENSE
codeoptix-0.1.3.dist-info/METADATA
codeoptix-0.1.3.dist-info/WHEEL
codeoptix-0.1.3.dist-info/entry_points.txt
codeoptix-0.1.3.dist-info/top_level.txt
codeoptix-0.1.3.dist-info/RECORD
