Metadata-Version: 2.4
Name: codeoptix
Version: 0.1.3
Summary: Agentic Code Optimization & Deep Evaluation for Superior Coding Agent Experience. Built by Superagentic AI.
Author-email: Shashi Jagtap <shashi@super-agentic.ai>, Shashi Jagtap <shashikant.jagtap@icloud.com>
Maintainer-email: Shashi Jagtap <team@super-agentic.ai>, Shashi Jagtap <shashikant.jagtap@icloud.com>
License: Apache-2.0
Project-URL: Homepage, https://github.com/SuperagenticAI/codeoptix
Project-URL: Documentation, https://superagenticai.github.io/codeoptix
Project-URL: Repository, https://github.com/SuperagenticAI/codeoptix
Project-URL: Issues, https://github.com/SuperagenticAI/codeoptix/issues
Project-URL: Changelog, https://github.com/SuperagenticAI/codeoptix/blob/main/CHANGELOG.md
Keywords: ai,coding-agents,behavioral-optimization,code-evaluation,agent-experience,deep-evaluation,agentic-coding
Classifier: Development Status :: 3 - Alpha
Classifier: Intended Audience :: Developers
Classifier: Intended Audience :: Science/Research
Classifier: License :: OSI Approved :: Apache Software License
Classifier: Programming Language :: Python :: 3
Classifier: Programming Language :: Python :: 3.12
Classifier: Topic :: Scientific/Engineering :: Artificial Intelligence
Classifier: Topic :: Software Development :: Libraries :: Python Modules
Classifier: Topic :: Software Development :: Quality Assurance
Classifier: Topic :: Software Development :: Testing
Classifier: Operating System :: OS Independent
Classifier: Framework :: Pydantic
Requires-Python: >=3.12
License-File: LICENSE
Requires-Dist: pydantic>=2.0.0
Requires-Dist: pyyaml>=6.0
Requires-Dist: click>=8.0.0
Requires-Dist: anthropic>=0.75.0
Requires-Dist: openai>=2.0.0
Requires-Dist: google-genai>=0.8.0
Requires-Dist: numpy>=1.24.0
Requires-Dist: litellm>=1.80.0
Requires-Dist: tenacity>=8.0.0
Requires-Dist: gepa==0.0.22
Requires-Dist: agent-client-protocol>=0.7.0
Provides-Extra: dev
Requires-Dist: pytest>=7.0.0; extra == "dev"
Requires-Dist: pytest-cov>=4.0.0; extra == "dev"
Requires-Dist: coverage>=7.0.0; extra == "dev"
Requires-Dist: ruff>=0.1.0; extra == "dev"
Requires-Dist: mypy>=1.0.0; extra == "dev"
Requires-Dist: pre-commit>=3.0.0; extra == "dev"
Provides-Extra: testing
Requires-Dist: pytest>=7.0.0; extra == "testing"
Requires-Dist: pytest-cov>=4.0.0; extra == "testing"
Requires-Dist: coverage>=7.0.0; extra == "testing"
Requires-Dist: bandit>=1.7.0; extra == "testing"
Provides-Extra: docs
Requires-Dist: mkdocs>=1.5.0; extra == "docs"
Requires-Dist: mkdocs-material>=9.4.0; extra == "docs"
Requires-Dist: pymdown-extensions>=10.0.0; extra == "docs"
Requires-Dist: mkdocs-minify-plugin>=0.7.0; extra == "docs"
Provides-Extra: all
Requires-Dist: codeoptix[dev,docs,testing]; extra == "all"
Provides-Extra: accessibility
Dynamic: license-file
